giefstat/__init__.py
giefstat/setting.py
giefstat/coefficient/__init__.py
giefstat/coefficient/corr_coeff/__init__.py
giefstat/coefficient/corr_coeff/coeff.py
giefstat/coefficient/mi_gief/__init__.py
giefstat/coefficient/mi_gief/entropy/__init__.py
giefstat/coefficient/mi_gief/entropy/cond_entropy.py
giefstat/coefficient/mi_gief/entropy/marg_entropy.py
giefstat/coefficient/mi_gief/mutual_info/__init__.py
giefstat/coefficient/mi_gief/mutual_info/_kraskov.py
giefstat/coefficient/mi_gief/mutual_info/_ross.py
giefstat/coefficient/mi_gief/mutual_info/cmi.py
giefstat/coefficient/mi_gief/mutual_info/mi.py
giefstat/coefficient/mi_kde/__init__.py
giefstat/coefficient/mi_kde/mi_kde.py
giefstat/coefficient/mi_model/__init__.py
giefstat/coefficient/mi_model/mi_cmi.py
giefstat/coefficient/mi_quant/__init__.py
giefstat/coefficient/mi_quant/_quant_darbellay.py
giefstat/coefficient/mi_quant/mi_classic.py
giefstat/coefficient/mi_quant/mi_darbellay.py
giefstat/coefficient/mic/__init__.py
giefstat/coefficient/mic/_mic_rmic.py
giefstat/coefficient/mic/mi_cmi.py
giefstat/independence_test/__init__.py
giefstat/independence_test/surrog_indep_test.py
giefstat/time_series/__init__.py
giefstat/time_series/partial_transfer_entropy.py
giefstat/time_series/td_assoc_analysis.py
giefstat/time_series/transfer_entropy.py
giefstat/time_series/util.py
giefstat/util/__init__.py
giefstat/util/univar_encoding.py
giefstat-1.0.0.dist-info/LICENSE
giefstat-1.0.0.dist-info/METADATA
giefstat-1.0.0.dist-info/WHEEL
giefstat-1.0.0.dist-info/top_level.txt
giefstat-1.0.0.dist-info/RECORD
