Metadata-Version: 2.1
Name: giefstat
Version: 1.0.0
Summary: Package for information estimation, independence test, causal structure mining, etc.
Home-page: https://github.com/Ulti-Dreisteine/general-information-estimation-framework
Author: Dreisteine
Author-email: dreisteine@163.com
License: MIT
Keywords: python,information estimation,time series,transfer entropy
Requires-Python: >=3.8.0
License-File: LICENSE
